telminal/__init__.py
telminal/__main__.py
telminal/core.py
telminal/main.py
telminal/telegram.py
telminal/utils.py
telminal/values.py
telminal-1.0.1.dist-info/LICENSE
telminal-1.0.1.dist-info/METADATA
telminal-1.0.1.dist-info/WHEEL
telminal-1.0.1.dist-info/entry_points.txt
telminal-1.0.1.dist-info/top_level.txt
telminal-1.0.1.dist-info/RECORD
