Metadata-Version: 2.1
Name: telminal
Version: 1.0.1
Summary: A Terminal in Telegram
Home-page: https://github.com/fristhon/telminal
Author: Mohammadreza Jafari
Author-email: fristhon@outlook.com
License: MIT
Platform: UNKNOWN
Classifier: License :: OSI Approved :: MIT License
Classifier: Programming Language :: Python :: 3
Classifier: Programming Language :: Python :: 3.7
Classifier: Programming Language :: Python :: 3.8
Classifier: Programming Language :: Python :: 3.9
Requires-Python: >=3.7
License-File: LICENSE
Requires-Dist: pexpect (<5,>=4.8.0)
Requires-Dist: Telethon (<2,>=1.23.0)
Requires-Dist: pyppeteer (>=0.2.6<1)
